CHANGELOG.txt
MANIFEST.in
Readme.txt
__init__.py
add.py
div.py
mult.py
setup.py
Harshit_Calculator.egg-info/PKG-INFO
Harshit_Calculator.egg-info/SOURCES.txt
Harshit_Calculator.egg-info/dependency_links.txt
Harshit_Calculator.egg-info/top_level.txt