Metadata-Version: 1.1
Name: Harshit-Calculator
Version: 0.0.1
Summary: Test_Calculator
Home-page:  
Author: Harshit
Author-email: llll@example.com
License: UNKNOWN
Keywords: add,div,mult
Platform: UNKNOWN
Classifier: Development Status :: 5 - Production/Stable
Classifier: Programming Language :: Python :: 3
